{"result":{"input":{"benchmark":{"id":"2020","benchmarkName":"Public_AR_Census2020","benchmarkDescription":"Public Address Ranges - Census 2020 Benchmark","isDefault":false},"address":{"address":"8 N Rowland,Richmond,VA"}},"addressMatches":[{"matchedAddress":"8 N ROWLAND ST, RICHMOND, VA, 23220","coordinates":{"x":-77.46702,"y":37.549805},"tigerLine":{"tigerLineId":"201536131","side":"L"},"addressComponents":{"fromAddress":"2","toAddress":"98","preQualifier":"","preDirection":"N","preType":"","streetName":"ROWLAND","suffixType":"ST","suffixDirection":"","suffixQualifier":"","city":"RICHMOND","state":"VA","zip":"23220"}}]}}